{
  "entries": {
    "tap": {
      "adoptopenjdk/openjdk": {
        "revision": "27915e4ab3856595a8b46d1fd3b6c379c1f02210"
      }
    },
    "cask": {
      "adoptopenjdk8": {
        "version": "8,292,b10",
        "options": {
          "full_name": "adoptopenjdk/openjdk/adoptopenjdk8"
        }
      },
      "adoptopenjdk11": {
        "version": "11.0.11,9",
        "options": {
          "full_name": "adoptopenjdk/openjdk/adoptopenjdk11"
        }
      }
    }
  },
  "system": {
    "macos": {
      "catalina": {
        "HOMEBREW_VERSION": "3.5.10-74-gd5b9d0e",
        "HOMEBREW_PREFIX": "/usr/local",
        "Homebrew/homebrew-core": "12a796617c3233fcbf2daa2aba483eec1304eb86",
        "CLT": "12.4.0.0.1.1610135815",
        "Xcode": "12.4",
        "macOS": "10.15.7"
      }
    }
  }
}
